<Library Version="1.1.0">
	<Material Version="1.4.0" Name="holdingline_south" Guid="{8F6C51B9-B199-4D28-8C41-3C713590A344}" SurfaceType="UNDEFINED" Type="CODE_DIFFUSE" Metal="0.000000" Rough="0.000000" Opacity="1.000000" BlendMode="Transparent">
		<TagList/>
		<FlagList/>
		<TextureList>
			<Texture FileName="TEXTURES\HOLDINGLINE_SOUTH.PNG.DDS" Binding="MTL_BITMAP_DECAL0"/>
		</TextureList>
		<Attributes>
			<Diffuse Red="1.000000" Green="1.000000" Blue="1.000000"/>
			<Emissive Red="0.000000" Green="0.000000" Blue="0.000000"/>
			<UVOffset U="0.000000" V="0.000000"/>
			<UVScale U="1.000000" V="1.000000"/>
			<UVRotate>0.000000</UVRotate>
			<ExtraParameters>
				<Parameter Value="0.000000"/>
				<Parameter Value="0.000000"/>
				<Parameter Value="0.000000"/>
				<Parameter Value="0.000000"/>
				<Parameter Value="0.000000"/>
				<Parameter Value="0.000000"/>
				<Parameter Value="0.000000"/>
				<Parameter Value="0.000000"/>
				<Parameter Value="0.000000"/>
				<Parameter Value="0.000000"/>
				<Parameter Value="0.000000"/>
				<Parameter Value="0.000000"/>
			</ExtraParameters>
		</Attributes>
	</Material>
	<Material Version="1.4.0" Name="marking_cross" Guid="{86CC30DB-1847-49EE-99D3-7C7CE63D4E10}" SurfaceType="UNDEFINED" Type="CODE_DIFFUSE" Metal="0.000000" Rough="0.000000" Opacity="1.000000" BlendMode="Transparent">
		<TagList/>
		<FlagList/>
		<TextureList>
			<Texture FileName="TEXTURES\MARKING_CROSS.PNG.DDS" Binding="MTL_BITMAP_DECAL0"/>
		</TextureList>
		<Attributes>
			<Diffuse Red="1.000000" Green="1.000000" Blue="1.000000"/>
			<Emissive Red="0.000000" Green="0.000000" Blue="0.000000"/>
			<UVOffset U="0.000000" V="0.000000"/>
			<UVScale U="1.000000" V="1.000000"/>
			<UVRotate>0.000000</UVRotate>
			<ExtraParameters>
				<Parameter Value="0.000000"/>
				<Parameter Value="0.000000"/>
				<Parameter Value="0.000000"/>
				<Parameter Value="0.000000"/>
				<Parameter Value="0.000000"/>
				<Parameter Value="0.000000"/>
				<Parameter Value="0.000000"/>
				<Parameter Value="0.000000"/>
				<Parameter Value="0.000000"/>
				<Parameter Value="0.000000"/>
				<Parameter Value="0.000000"/>
				<Parameter Value="0.000000"/>
			</ExtraParameters>
		</Attributes>
	</Material>
	<Material Version="1.4.0" Name="grid_south" Guid="{6FE9DB99-D14A-47F1-8C09-31BB6DE6FE41}" SurfaceType="UNDEFINED" Type="CODE_DIFFUSE" Metal="0.000000" Rough="0.000000" Opacity="1.000000" BlendMode="Transparent">
		<TagList/>
		<FlagList/>
		<TextureList>
			<Texture FileName="TEXTURES\GRID_SOUTH.PNG.DDS" Binding="MTL_BITMAP_DECAL0"/>
		</TextureList>
		<Attributes>
			<Diffuse Red="1.000000" Green="1.000000" Blue="1.000000"/>
			<Emissive Red="0.000000" Green="0.000000" Blue="0.000000"/>
			<UVOffset U="0.000000" V="0.000000"/>
			<UVScale U="1.000000" V="1.000000"/>
			<UVRotate>0.000000</UVRotate>
			<ExtraParameters>
				<Parameter Value="0.000000"/>
				<Parameter Value="0.000000"/>
				<Parameter Value="0.000000"/>
				<Parameter Value="0.000000"/>
				<Parameter Value="0.000000"/>
				<Parameter Value="0.000000"/>
				<Parameter Value="0.000000"/>
				<Parameter Value="0.000000"/>
				<Parameter Value="0.000000"/>
				<Parameter Value="0.000000"/>
				<Parameter Value="0.000000"/>
				<Parameter Value="0.000000"/>
			</ExtraParameters>
		</Attributes>
	</Material>
	<Material Version="1.4.0" Name="18" Guid="{BB47E98B-7C46-46DE-90CF-F6CA583502D9}" SurfaceType="UNDEFINED" Type="CODE_DIFFUSE" Metal="0.000000" Rough="0.000000" Opacity="1.000000" BlendMode="Transparent">
		<TagList/>
		<FlagList/>
		<TextureList>
			<Texture FileName="TEXTURES\18.PNG.DDS" Binding="MTL_BITMAP_DECAL0"/>
		</TextureList>
		<Attributes>
			<Diffuse Red="1.000000" Green="1.000000" Blue="1.000000"/>
			<Emissive Red="0.000000" Green="0.000000" Blue="0.000000"/>
			<UVOffset U="0.000000" V="0.000000"/>
			<UVScale U="1.000000" V="1.000000"/>
			<UVRotate>0.000000</UVRotate>
			<ExtraParameters>
				<Parameter Value="0.000000"/>
				<Parameter Value="0.000000"/>
				<Parameter Value="0.000000"/>
				<Parameter Value="0.000000"/>
				<Parameter Value="0.000000"/>
				<Parameter Value="0.000000"/>
				<Parameter Value="0.000000"/>
				<Parameter Value="0.000000"/>
				<Parameter Value="0.000000"/>
				<Parameter Value="0.000000"/>
				<Parameter Value="0.000000"/>
				<Parameter Value="0.000000"/>
			</ExtraParameters>
		</Attributes>
	</Material>
	<Material Version="1.4.0" Name="36" Guid="{51011414-4BD2-416E-9534-A3CA1E191C7F}" SurfaceType="UNDEFINED" Type="CODE_DIFFUSE" Metal="0.000000" Rough="0.000000" Opacity="1.000000" BlendMode="Transparent">
		<TagList/>
		<FlagList/>
		<TextureList>
			<Texture FileName="TEXTURES\36.PNG.DDS" Binding="MTL_BITMAP_DECAL0"/>
		</TextureList>
		<Attributes>
			<Diffuse Red="1.000000" Green="1.000000" Blue="1.000000"/>
			<Emissive Red="0.000000" Green="0.000000" Blue="0.000000"/>
			<UVOffset U="0.000000" V="0.000000"/>
			<UVScale U="1.000000" V="1.000000"/>
			<UVRotate>0.000000</UVRotate>
			<ExtraParameters>
				<Parameter Value="0.000000"/>
				<Parameter Value="0.000000"/>
				<Parameter Value="0.000000"/>
				<Parameter Value="0.000000"/>
				<Parameter Value="0.000000"/>
				<Parameter Value="0.000000"/>
				<Parameter Value="0.000000"/>
				<Parameter Value="0.000000"/>
				<Parameter Value="0.000000"/>
				<Parameter Value="0.000000"/>
				<Parameter Value="0.000000"/>
				<Parameter Value="0.000000"/>
			</ExtraParameters>
		</Attributes>
	</Material>
	<Material Version="1.4.0" Name="grid_north" Guid="{D60EC9A7-5A04-4167-A239-E904E10411B3}" SurfaceType="UNDEFINED" Type="CODE_DIFFUSE" Metal="0.000000" Rough="0.000000" Opacity="1.000000" BlendMode="Transparent">
		<TagList/>
		<FlagList/>
		<TextureList>
			<Texture FileName="TEXTURES\GRID_NORTH.PNG.DDS" Binding="MTL_BITMAP_DECAL0"/>
		</TextureList>
		<Attributes>
			<Diffuse Red="1.000000" Green="1.000000" Blue="1.000000"/>
			<Emissive Red="0.000000" Green="0.000000" Blue="0.000000"/>
			<UVOffset U="0.000000" V="0.000000"/>
			<UVScale U="1.000000" V="1.000000"/>
			<UVRotate>0.000000</UVRotate>
			<ExtraParameters>
				<Parameter Value="0.000000"/>
				<Parameter Value="0.000000"/>
				<Parameter Value="0.000000"/>
				<Parameter Value="0.000000"/>
				<Parameter Value="0.000000"/>
				<Parameter Value="0.000000"/>
				<Parameter Value="0.000000"/>
				<Parameter Value="0.000000"/>
				<Parameter Value="0.000000"/>
				<Parameter Value="0.000000"/>
				<Parameter Value="0.000000"/>
				<Parameter Value="0.000000"/>
			</ExtraParameters>
		</Attributes>
	</Material>
	<Material Version="1.4.0" Name="centerline" Guid="{8AEA6F3B-E93E-45CE-A3C7-19A7A6847BE4}" SurfaceType="UNDEFINED" Type="CODE_DIFFUSE" Metal="0.000000" Rough="0.000000" Opacity="1.000000" BlendMode="Transparent">
		<TagList/>
		<FlagList/>
		<TextureList>
			<Texture FileName="TEXTURES\CENTERLINE.PNG.DDS" Binding="MTL_BITMAP_DECAL0"/>
		</TextureList>
		<Attributes>
			<Diffuse Red="1.000000" Green="1.000000" Blue="1.000000"/>
			<Emissive Red="0.000000" Green="0.000000" Blue="0.000000"/>
			<UVOffset U="0.000000" V="0.000000"/>
			<UVScale U="1.000000" V="1.000000"/>
			<UVRotate>0.000000</UVRotate>
			<ExtraParameters>
				<Parameter Value="0.000000"/>
				<Parameter Value="0.000000"/>
				<Parameter Value="0.000000"/>
				<Parameter Value="0.000000"/>
				<Parameter Value="0.000000"/>
				<Parameter Value="0.000000"/>
				<Parameter Value="0.000000"/>
				<Parameter Value="0.000000"/>
				<Parameter Value="0.000000"/>
				<Parameter Value="0.000000"/>
				<Parameter Value="0.000000"/>
				<Parameter Value="0.000000"/>
			</ExtraParameters>
		</Attributes>
	</Material>
	<Material Version="1.4.0" Name="holdingline_north" Guid="{14457097-7BE2-4FC8-96CD-D47D108ACD4A}" SurfaceType="UNDEFINED" Type="CODE_DIFFUSE" Metal="0.000000" Rough="0.000000" Opacity="1.000000" BlendMode="Transparent">
		<TagList/>
		<FlagList/>
		<TextureList>
			<Texture FileName="TEXTURES\HOLDINGLINE_NORTH.PNG.DDS" Binding="MTL_BITMAP_DECAL0"/>
		</TextureList>
		<Attributes>
			<Diffuse Red="1.000000" Green="1.000000" Blue="1.000000"/>
			<Emissive Red="0.000000" Green="0.000000" Blue="0.000000"/>
			<UVOffset U="0.000000" V="0.000000"/>
			<UVScale U="1.000000" V="1.000000"/>
			<UVRotate>0.000000</UVRotate>
			<ExtraParameters>
				<Parameter Value="0.000000"/>
				<Parameter Value="0.000000"/>
				<Parameter Value="0.000000"/>
				<Parameter Value="0.000000"/>
				<Parameter Value="0.000000"/>
				<Parameter Value="0.000000"/>
				<Parameter Value="0.000000"/>
				<Parameter Value="0.000000"/>
				<Parameter Value="0.000000"/>
				<Parameter Value="0.000000"/>
				<Parameter Value="0.000000"/>
				<Parameter Value="0.000000"/>
			</ExtraParameters>
		</Attributes>
	</Material>
	<Material Version="1.4.0" Name="threshold" Guid="{53E5024F-A872-4F30-AA4B-83A06D9DAC8B}" SurfaceType="UNDEFINED" Type="CODE_DIFFUSE" Metal="0.000000" Rough="0.000000" Opacity="1.000000" BlendMode="Transparent">
		<TagList/>
		<FlagList/>
		<TextureList>
			<Texture FileName="TEXTURES\THRESHOLD.PNG.DDS" Binding="MTL_BITMAP_DECAL0"/>
		</TextureList>
		<Attributes>
			<Diffuse Red="1.000000" Green="1.000000" Blue="1.000000"/>
			<Emissive Red="0.000000" Green="0.000000" Blue="0.000000"/>
			<UVOffset U="0.000000" V="0.000000"/>
			<UVScale U="1.000000" V="1.000000"/>
			<UVRotate>0.000000</UVRotate>
			<ExtraParameters>
				<Parameter Value="0.000000"/>
				<Parameter Value="0.000000"/>
				<Parameter Value="0.000000"/>
				<Parameter Value="0.000000"/>
				<Parameter Value="0.000000"/>
				<Parameter Value="0.000000"/>
				<Parameter Value="0.000000"/>
				<Parameter Value="0.000000"/>
				<Parameter Value="0.000000"/>
				<Parameter Value="0.000000"/>
				<Parameter Value="0.000000"/>
				<Parameter Value="0.000000"/>
			</ExtraParameters>
		</Attributes>
	</Material>
	<Material Version="1.4.0" Name="holdingline_mid" Guid="{1128B835-DD4C-4EC1-B5F3-C590857C552E}" SurfaceType="UNDEFINED" Type="CODE_DIFFUSE" Metal="0.000000" Rough="0.000000" Opacity="1.000000" BlendMode="Transparent">
		<TagList/>
		<FlagList/>
		<TextureList>
			<Texture FileName="TEXTURES\HOLDINGLINE_MID.PNG.DDS" Binding="MTL_BITMAP_DECAL0"/>
		</TextureList>
		<Attributes>
			<Diffuse Red="1.000000" Green="1.000000" Blue="1.000000"/>
			<Emissive Red="0.000000" Green="0.000000" Blue="0.000000"/>
			<UVOffset U="0.000000" V="0.000000"/>
			<UVScale U="1.000000" V="1.000000"/>
			<UVRotate>0.000000</UVRotate>
			<ExtraParameters>
				<Parameter Value="0.000000"/>
				<Parameter Value="0.000000"/>
				<Parameter Value="0.000000"/>
				<Parameter Value="0.000000"/>
				<Parameter Value="0.000000"/>
				<Parameter Value="0.000000"/>
				<Parameter Value="0.000000"/>
				<Parameter Value="0.000000"/>
				<Parameter Value="0.000000"/>
				<Parameter Value="0.000000"/>
				<Parameter Value="0.000000"/>
				<Parameter Value="0.000000"/>
			</ExtraParameters>
		</Attributes>
	</Material>
</Library>

